odoo8_addon_account_voucher_source_document-8.0.1.0.0.99.dev9-py2.7-nspkg.pth
odoo8_addon_account_voucher_source_document-8.0.1.0.0.99.dev9.dist-info/METADATA
odoo8_addon_account_voucher_source_document-8.0.1.0.0.99.dev9.dist-info/RECORD
odoo8_addon_account_voucher_source_document-8.0.1.0.0.99.dev9.dist-info/WHEEL
odoo8_addon_account_voucher_source_document-8.0.1.0.0.99.dev9.dist-info/namespace_packages.txt
odoo8_addon_account_voucher_source_document-8.0.1.0.0.99.dev9.dist-info/top_level.txt
odoo_addons/account_voucher_source_document/README.rst
odoo_addons/account_voucher_source_document/__init__.py
odoo_addons/account_voucher_source_document/__openerp__.py
odoo_addons/account_voucher_source_document/i18n/account_voucher_source_document.pot
odoo_addons/account_voucher_source_document/i18n/de.po
odoo_addons/account_voucher_source_document/i18n/fr.po
odoo_addons/account_voucher_source_document/i18n/sl.po
odoo_addons/account_voucher_source_document/models/__init__.py
odoo_addons/account_voucher_source_document/models/account_voucher.py
odoo_addons/account_voucher_source_document/models/account_voucher_line.py
odoo_addons/account_voucher_source_document/static/description/icon.png
odoo_addons/account_voucher_source_document/tests/__init__.py
odoo_addons/account_voucher_source_document/tests/test_account_voucher.py
odoo_addons/account_voucher_source_document/views/account_voucher.xml
