Metadata-Version: 2.1
Name: odoo8-addon-account-voucher-source-document
Version: 8.0.1.0.0.99.dev9
Summary: Source Document in Customer Payments
Home-page: http://www.agilebg.com
Author: Agile Business Group sagl,Savoir-faire linux,Odoo Community Association
Author-email: UNKNOWN
License: AGPL-3
Platform: UNKNOWN
Classifier: Programming Language :: Python
Classifier: Framework :: Odoo
Classifier: License :: OSI Approved :: GNU Affero General Public License v3
Requires-Python: ~=2.7
Requires-Dist: odoo (<9.0a,>=8.0a)
